cc410/__init__.py
cc410/conftest.py
cc410/register/CardReader.py
cc410/register/CardTransactionResult.py
cc410/register/CashDenomination.py
cc410/register/CashDrawer.py
cc410/register/ReceiptPrinter.py
cc410/register/__init__.py
test/__init__.py
test/register/FakeDate.py
test/register/__init__.py
test/register/test_CardReader.py
test/register/test_CardTransactionResult.py
test/register/test_CashDenomination.py
test/register/test_CashDrawer.py
test/register/test_ReceiptPrinter.py
cc410_restaurant_register-1.0.5.dist-info/LICENSE
cc410_restaurant_register-1.0.5.dist-info/METADATA
cc410_restaurant_register-1.0.5.dist-info/WHEEL
cc410_restaurant_register-1.0.5.dist-info/top_level.txt
cc410_restaurant_register-1.0.5.dist-info/RECORD
