Metadata-Version: 2.1
Name: cc410-restaurant-register
Version: 1.0.5
Summary: CC 410 Register
Home-page: https://github.com/russfeld/restaurantregister-python
Author: Russell Feldhausen
Author-email: russfeld@ksu.edu
License: UNKNOWN
Project-URL: Bug Tracker, https://github.com/russfeld/restaurantregister-python/issues
Platform: UNKNOWN
Classifier: Programming Language :: Python :: 3
Classifier: License :: OSI Approved :: MIT License
Classifier: Operating System :: OS Independent
Requires-Python: >=3.6
License-File: LICENSE
